vice/__init__.py
vice/vice.py
pygments_vice-0.1.3.dist-info/LICENSE
pygments_vice-0.1.3.dist-info/METADATA
pygments_vice-0.1.3.dist-info/WHEEL
pygments_vice-0.1.3.dist-info/entry_points.txt
pygments_vice-0.1.3.dist-info/top_level.txt
pygments_vice-0.1.3.dist-info/RECORD
